methyltree/QC.py
methyltree/__init__.py
methyltree/adata.py
methyltree/analysis.py
methyltree/barcode_map.csv
methyltree/batch.py
methyltree/clone.py
methyltree/help_functions.py
methyltree/lineage.py
methyltree/metadata.py
methyltree/metric.py
methyltree/plotting.py
methyltree/region.py
methyltree/scripts.py
methyltree/settings.py
methyltree/similarity.py
methyltree/simulation.py
methyltree-0.1.1.dist-info/LICENSE-CC-BY-NC-4.0.md
methyltree-0.1.1.dist-info/METADATA
methyltree-0.1.1.dist-info/WHEEL
methyltree-0.1.1.dist-info/RECORD
