Metadata-Version: 2.3
Name: methyltree
Version: 0.1.1
Summary: High-resolution, noninvasive single-cell lineage tracing based on DNA methylation epimutations.
License: Proprietary
Author: ShouWenWang
Author-email: wangshouwen@westlake.edu.cn
Requires-Python: >=3.9,<3.12
Classifier: License :: Other/Proprietary License
Classifier: Programming Language :: Python :: 3
Classifier: Programming Language :: Python :: 3.9
Classifier: Programming Language :: Python :: 3.10
Classifier: Programming Language :: Python :: 3.11
Requires-Dist: anndata (>=0.9.2,<0.10.0)
Requires-Dist: biopython (==1.82)
Requires-Dist: biotite (==0.38.0)
Requires-Dist: cospar (>=0.4.1,<0.5.0)
Requires-Dist: dendropy (==4.6.1)
Requires-Dist: ete3 (>=3.1.3,<4.0.0)
Requires-Dist: fastcluster (>=1.2.6,<2.0.0)
Requires-Dist: gseapy (>=1.1.3,<2.0.0)
Requires-Dist: ipython (==8.18.1)
Requires-Dist: jupyterlab (>=4.2.0)
Requires-Dist: leidenalg (>=0.10.2,<0.11.0)
Requires-Dist: matplotlib (>=3.7.3,<3.8.0)
Requires-Dist: multiprocess (==0.70.16)
Requires-Dist: numpy (>=1.24.4,<2.0.0)
Requires-Dist: pandas (>=2.0.3,<3.0.0)
Requires-Dist: plotnine (>=0.12.4,<0.13.0)
Requires-Dist: pot (==0.9.2)
Requires-Dist: pyranges (==0.0.129)
Requires-Dist: pyyaml (==6.0.1)
Requires-Dist: scanpy (>=1.9.8,<2.0.0)
Requires-Dist: scikit-bio (==0.5.9)
Requires-Dist: scikit-learn (>=1.1.3,<1.2.0)
Requires-Dist: scikit-misc (>=0.1.4,<0.3.0)
Requires-Dist: scipy (<=1.13.1)
Requires-Dist: seaborn (==0.13.2)
Requires-Dist: statsmodels (>=0.14.2,<0.15.0)
Requires-Dist: tqdm (>=4.66.5,<5.0.0)
Requires-Dist: wand (==0.6.13)
